codon_usage_data/codon_usage_retriever.py
codon_usage_data/organisms.csv
codon_usage_data/version.txt
codon_usage_data/tables/b_subtilis_1423.csv
codon_usage_data/tables/c_elegans_6239.csv
codon_usage_data/tables/d_melanogaster_7227.csv
codon_usage_data/tables/e_coli_316407.csv
codon_usage_data/tables/g_gallus_9031.csv
codon_usage_data/tables/h_sapiens_9606.csv
codon_usage_data/tables/m_musculus_10090.csv
codon_usage_data/tables/m_musculus_domesticus_10092.csv
codon_usage_data/tables/s_cerevisiae_4932.csv
python_codon_tables/README.rst
python_codon_tables/__init__.py
python_codon_tables/ez_setup.py
python_codon_tables/python_codon_tables.py
python_codon_tables-0.1.13.dist-info/LICENSE
python_codon_tables-0.1.13.dist-info/METADATA
python_codon_tables-0.1.13.dist-info/WHEEL
python_codon_tables-0.1.13.dist-info/top_level.txt
python_codon_tables-0.1.13.dist-info/RECORD
