Metadata-Version: 2.1
Name: python_codon_tables
Version: 0.1.13
Summary: Codon Usage Tables for Python, from kazusa.or.jp
Home-page: https://github.com/Edinburgh-Genome-Foundry/codon-usage-tables
Author: Zulko
License: Public Domain
Keywords: DNA codon usage
License-File: LICENSE
